bitcoin_network_tools/__init__.py
bitcoin_network_tools/bitnodes_api.py
bitcoin_network_tools/tests/__init__.py
bitcoin_network_tools/tests/test_bitnodes_api.py
bitcoin_network_tools-0.0.1.dist-info/LICENSE
bitcoin_network_tools-0.0.1.dist-info/METADATA
bitcoin_network_tools-0.0.1.dist-info/WHEEL
bitcoin_network_tools-0.0.1.dist-info/entry_points.txt
bitcoin_network_tools-0.0.1.dist-info/top_level.txt
bitcoin_network_tools-0.0.1.dist-info/RECORD
