Metadata-Version: 2.1
Name: bitcoin_network_tools
Version: 0.0.1
Summary: A wrapper for the Bitnodes API.
Author-email: "Zachary A. Kraehling" <zak@zakkraehling.net>
License: Apache Software License
Project-URL: homepage, https://github.com/7astro7/bitcoin-network-tools
Project-URL: repository, https://github.com/7astro7/bitcoin-network-tools
Project-URL: issues, https://github.com/7astro7/bitcoin-network-tools/issues
Keywords: bitcoin,blockchain,cryptocurrency,network analysis,bitnodes,api,tools,python,development,crypto,financial technology,decentralized networks
Classifier: Programming Language :: Python :: 3
Classifier: License :: OSI Approved :: Apache Software License
Classifier: Operating System :: OS Independent
Classifier: Topic :: Software Development :: Libraries :: Python Modules
Classifier: Intended Audience :: Developers
Classifier: Intended Audience :: Science/Research
Classifier: Topic :: Scientific/Engineering :: Information Analysis
Classifier: Topic :: Internet :: WWW/HTTP
Requires-Python: >=3.6
License-File: LICENSE
Requires-Dist: requests>=2.32.3
Requires-Dist: dnspython>=2.7.0
Provides-Extra: dev
Requires-Dist: pytest; extra == "dev"
Requires-Dist: flake8; extra == "dev"
